<?xml version="1.0" encoding="UTF-8"?><record_update>
    <sys_ui_section action="DELETE" caption="Plan description" section_id="a4a50ee1dbaed410faa711494b96195c" sys_domain="global" table="x_anbib_grc_action_plan_control_implementation" version="3" view="">
        <sys_ui_element action="INSERT_OR_UPDATE">
            <element>action_plan_description</element>
            <position>0</position>
            <sys_created_by>nathalia.zago@alparservice.com.br</sys_created_by>
            <sys_created_on>2020-09-17 14:11:37</sys_created_on>
            <sys_id>4a1225bddbd35c90faa711494b96197a</sys_id>
            <sys_mod_count>0</sys_mod_count>
            <sys_ui_formatter/>
            <sys_ui_section caption="Plan description" display_value="Plan description" name="x_anbib_grc_action_plan_control_implementation" sys_domain="global" view="Default view">a4a50ee1dbaed410faa711494b96195c</sys_ui_section>
            <sys_updated_by>nathalia.zago@alparservice.com.br</sys_updated_by>
            <sys_updated_on>2020-09-17 14:11:37</sys_updated_on>
            <sys_user/>
            <type/>
        </sys_ui_element>
        <sys_ui_section action="DELETE">
            <caption>Plan description</caption>
            <header>false</header>
            <name>x_anbib_grc_action_plan_control_implementation</name>
            <roles/>
            <sys_class_name>sys_ui_section</sys_class_name>
            <sys_created_by>marcos.michalski@alparservice.com.br</sys_created_by>
            <sys_created_on>2020-08-10 15:21:19</sys_created_on>
            <sys_domain>global</sys_domain>
            <sys_domain_path>/</sys_domain_path>
            <sys_id>a4a50ee1dbaed410faa711494b96195c</sys_id>
            <sys_mod_count>0</sys_mod_count>
            <sys_name>Plan description</sys_name>
            <sys_overrides/>
            <sys_package display_value="GRC" source="x_anbib_grc">1a6d93de1b6d58504aae202a2d4bcbdc</sys_package>
            <sys_policy/>
            <sys_scope display_value="GRC">1a6d93de1b6d58504aae202a2d4bcbdc</sys_scope>
            <sys_update_name>sys_ui_section_a4a50ee1dbaed410faa711494b96195c</sys_update_name>
            <sys_updated_by>marcos.michalski@alparservice.com.br</sys_updated_by>
            <sys_updated_on>2020-08-10 15:21:19</sys_updated_on>
            <sys_user/>
            <title>false</title>
            <view display_value="Default view" name="NULL">Default view</view>
            <view_name/>
        </sys_ui_section>
    </sys_ui_section>
    <sys_update_version action="INSERT_OR_UPDATE">
        <action>DELETE</action>
        <application display_value="GRC">1a6d93de1b6d58504aae202a2d4bcbdc</application>
        <file_path/>
        <instance_id>316b55b0db2580184d2bac44d496199a</instance_id>
        <instance_name>abinbevwwqa</instance_name>
        <name>sys_ui_section_a4a50ee1dbaed410faa711494b96195c</name>
        <payload><![CDATA[<?xml version="1.0" encoding="UTF-8"?><record_update><sys_ui_section caption="Plan description" section_id="a4a50ee1dbaed410faa711494b96195c" sys_domain="global" table="x_anbib_grc_action_plan_control_implementation" version="3" view=""><sys_ui_element action="INSERT_OR_UPDATE"><element>action_plan_description</element><position>0</position><sys_created_by>nathalia.zago@alparservice.com.br</sys_created_by><sys_created_on>2020-09-17 14:11:37</sys_created_on><sys_id>4a1225bddbd35c90faa711494b96197a</sys_id><sys_mod_count>0</sys_mod_count><sys_ui_formatter/><sys_ui_section caption="Plan description" display_value="Plan description" name="x_anbib_grc_action_plan_control_implementation" sys_domain="global" view="Default view">a4a50ee1dbaed410faa711494b96195c</sys_ui_section><sys_updated_by>nathalia.zago@alparservice.com.br</sys_updated_by><sys_updated_on>2020-09-17 14:11:37</sys_updated_on><sys_user/><type/></sys_ui_element><sys_ui_section action="INSERT_OR_UPDATE"><caption>Plan description</caption><header>false</header><name>x_anbib_grc_action_plan_control_implementation</name><roles/><sys_class_name>sys_ui_section</sys_class_name><sys_created_by>marcos.michalski@alparservice.com.br</sys_created_by><sys_created_on>2020-08-10 15:21:19</sys_created_on><sys_domain>global</sys_domain><sys_domain_path>/</sys_domain_path><sys_id>a4a50ee1dbaed410faa711494b96195c</sys_id><sys_mod_count>0</sys_mod_count><sys_name>Plan description</sys_name><sys_overrides/><sys_package display_value="GRC" source="x_anbib_grc">1a6d93de1b6d58504aae202a2d4bcbdc</sys_package><sys_policy/><sys_scope display_value="GRC">1a6d93de1b6d58504aae202a2d4bcbdc</sys_scope><sys_update_name>sys_ui_section_a4a50ee1dbaed410faa711494b96195c</sys_update_name><sys_updated_by>marcos.michalski@alparservice.com.br</sys_updated_by><sys_updated_on>2020-08-10 15:21:19</sys_updated_on><sys_user/><title>false</title><view display_value="Default view" name="NULL">Default view</view><view_name/></sys_ui_section></sys_ui_section></record_update>]]></payload>
        <payload_hash>2059279044</payload_hash>
        <record_name>Control Implementation Action Plan</record_name>
        <reverted_from/>
        <source>d1ac4bf0db1f5c5002085bd05b961990</source>
        <source_table>sys_update_set</source_table>
        <state>previous</state>
        <sys_created_by>nathalia.zago@alparservice.com.br</sys_created_by>
        <sys_created_on>2020-09-17 14:11:37</sys_created_on>
        <sys_id>461225bddbd35c90faa711494b96197c</sys_id>
        <sys_mod_count>0</sys_mod_count>
        <sys_recorded_at>1749c6807ed0000001</sys_recorded_at>
        <sys_updated_by>nathalia.zago@alparservice.com.br</sys_updated_by>
        <sys_updated_on>2020-09-17 14:11:37</sys_updated_on>
        <type>Form Layout</type>
        <update_guid>0e1225bd0bd35c902a92b0f704b9e17b</update_guid>
        <update_guid_history>0e1225bd0bd35c902a92b0f704b9e17b:2059279044,2da0edf50ed35c90b635614169a6a367:-336480405,0ddb4bf6a3c754102beed84056dbc188:0,359a83be8087541066d11036d0a84728:-1112927868,476b895dfd879c50e08a2e7beabedbc4:0,d58a0dd5f1879c505cd417a995ed0e7e:-1112927868,df848dd597479c501312b2e9f06705cb:0,ef938951d4479c503950b03aff698797:-1112927868,03424ac98bc31c504e5f04923b96f5fe:0,51018a057ac31c502873beb0103b11f9:-1112927868,b3b2cc851c8f9850ed70ec768cd6aab2:0,0a2188c95f4f98506cb84dba39e20b04:-1112927868,a6044cb8a0075850c54b56f605221364:0,491304745a075850f882aaf8e83ec4c7:-1112927868,c0aa626438cb18509b3472dbc93705cf:0,977962203ecb1850256ff0b0d5bf904b:-1112927868,da152268c78b1850a96364398e3d057b:0,65046224b28b185025a5902c5ef5affc:-1112927868,9850e354694fd4504002ae26294410dd:0,270f1bdc8d0fd450d6555b07fab0cbbb:-1112927868,e4505b98a38bd450dc4f3f2c0ef2f6d4:0,930fcf10fd8bd450b94d84b9897cca51:-1112927868,3b9c8fd0d14bd4503187289fa49f73b2:0,bf4b07186c0bd450ace8196547306c73:-1112927868,5729039cb4c7d450479ed0d1770e586f:0,1ab70f5092c7d450cb278fff8be366ba:-1112927868,c15207d86747d4500b29ec7b19a91204:0,5fb0075cf707d450c684a8b371de84dc:-1112927868,e99f3ed48e07d450496ceea020b6a043:0,923ebe9849c3d450984891ccb6729c88:-1112927868,407c36506dc3d4509a2100866596954b:0,a30bb6148883d45033680570142ca876:-1112927868,fc597ed83943d450559633f830e5fe9c:0,0cf73a9c0103d4504f510a5014efdd06:-1112927868,3f73f2d891cf94505c4a8c2445db4eba:0,23e17a1c5f8f945025cd72990f8b6c6b:-1112927868,90b9a6d8e04f9450882bca39a81c3be5:0,6718e2508f4f9450a367c41b2c6cc1f7:-1112927868,4a57ce98948b9450f7b5c6d900fae9ea:0,25c58e50088b9450cf18b3e969818546:-1112927868,2553c25c194b945090374a8796c26652:0,96d18254134b94502ee2e7ac8b39c1f5:-1112927868,06af7110724b9450ff19e9a61e48e239:0,2d2e31d41d0b94503eedc56647cd4f41:-1112927868,8a5cb990fc0b9450d36b149a30a56bf5:0,edca3198e8c794505925c951c394fb71:-1112927868,7fbe6510968794500c7cb71d35e231bf:0,bc1dedd42b479450694fba540806fb3b:-1112927868,7e4333df8e36dc10da10cbcfea0dfb06:0,fb22f3978536dc104ce5bbe574486917:-1112927868,189e2b5f74f2dc106ec724ec44319e95:0,026d635768f2dc10e04c94eaf8acfb02:-1112927868,61dca793cbf2dc10804c9843dd8df9ae:0,498b275b14b2dc10d0ba5121c2cde018:-1112927868,70a54ee1b6aed4103013b34db93b8410:2059279044</update_guid_history>
    </sys_update_version>
    <sys_metadata_delete action="INSERT_OR_UPDATE">
        <sys_audit_delete/>
        <sys_class_name>sys_metadata_delete</sys_class_name>
        <sys_created_by>nathalia.zago@alparservice.com.br</sys_created_by>
        <sys_created_on>2020-09-17 17:03:41</sys_created_on>
        <sys_db_object display_value="" name="sys_ui_section">sys_ui_section</sys_db_object>
        <sys_id>3f289470e7fb4b2ca72b1fa2e8619ee4</sys_id>
        <sys_metadata>a4a50ee1dbaed410faa711494b96195c</sys_metadata>
        <sys_mod_count>0</sys_mod_count>
        <sys_name>Plan description</sys_name>
        <sys_package display_value="GRC" source="x_anbib_grc">1a6d93de1b6d58504aae202a2d4bcbdc</sys_package>
        <sys_parent display_value="Control Implementation Action Plan">3da4c261dbaed410faa711494b961924</sys_parent>
        <sys_policy/>
        <sys_scope display_value="GRC">1a6d93de1b6d58504aae202a2d4bcbdc</sys_scope>
        <sys_scope_delete display_value="">4282d7e0d78843f5a3fb6c4300e2df09</sys_scope_delete>
        <sys_update_name>sys_ui_section_a4a50ee1dbaed410faa711494b96195c</sys_update_name>
        <sys_update_version display_value="sys_ui_section_a4a50ee1dbaed410faa711494b96195c">461225bddbd35c90faa711494b96197c</sys_update_version>
        <sys_updated_by>nathalia.zago@alparservice.com.br</sys_updated_by>
        <sys_updated_on>2020-09-17 17:03:41</sys_updated_on>
    </sys_metadata_delete>
</record_update>
