<?xml version="1.0" encoding="UTF-8"?><record_update>
    <sys_choice action="INSERT_OR_UPDATE" field="state" table="x_anbib_grc_action_plan_control_implementation" version="3">
        <sys_choice action="INSERT_OR_UPDATE">
            <dependent_value/>
            <element>state</element>
            <hint/>
            <inactive>false</inactive>
            <label>Draft</label>
            <language>en</language>
            <name>x_anbib_grc_action_plan_control_implementation</name>
            <sequence>0</sequence>
            <sys_created_by>marcos.michalski@alparservice.com.br</sys_created_by>
            <sys_created_on>2020-08-11 15:26:03</sys_created_on>
            <sys_domain>global</sys_domain>
            <sys_domain_path>/</sys_domain_path>
            <sys_id>f830d331db22d810faa711494b96195a</sys_id>
            <sys_mod_count>3</sys_mod_count>
            <sys_updated_by>nathalia.zago@alparservice.com.br</sys_updated_by>
            <sys_updated_on>2020-09-08 13:50:25</sys_updated_on>
            <value>1</value>
        </sys_choice>
        <sys_choice action="INSERT_OR_UPDATE">
            <dependent_value/>
            <element>state</element>
            <hint/>
            <inactive>true</inactive>
            <label>Wait for implementation</label>
            <language>en</language>
            <name>x_anbib_grc_action_plan_control_implementation</name>
            <sequence>0</sequence>
            <sys_created_by>nathalia.zago@alparservice.com.br</sys_created_by>
            <sys_created_on>2020-09-08 13:50:25</sys_created_on>
            <sys_domain>global</sys_domain>
            <sys_domain_path>/</sys_domain_path>
            <sys_id>37e68b76db875410faa711494b961961</sys_id>
            <sys_mod_count>1</sys_mod_count>
            <sys_updated_by>nathalia.zago@alparservice.com.br</sys_updated_by>
            <sys_updated_on>2020-09-08 13:57:20</sys_updated_on>
            <value>14</value>
        </sys_choice>
        <sys_choice action="INSERT_OR_UPDATE">
            <dependent_value/>
            <element>state</element>
            <hint/>
            <inactive>true</inactive>
            <label>Approved</label>
            <language>en</language>
            <name>x_anbib_grc_action_plan_control_implementation</name>
            <sequence>0</sequence>
            <sys_created_by>marcos.michalski@alparservice.com.br</sys_created_by>
            <sys_created_on>2020-08-13 13:09:12</sys_created_on>
            <sys_domain>global</sys_domain>
            <sys_domain_path>/</sys_domain_path>
            <sys_id>2c2401e6dbe2dc1002085bd05b961952</sys_id>
            <sys_mod_count>5</sys_mod_count>
            <sys_updated_by>nathalia.zago@alparservice.com.br</sys_updated_by>
            <sys_updated_on>2020-09-08 18:40:37</sys_updated_on>
            <value>4</value>
        </sys_choice>
        <sys_choice action="INSERT_OR_UPDATE">
            <dependent_value/>
            <element>state</element>
            <hint/>
            <inactive>false</inactive>
            <label>In validation</label>
            <language>en</language>
            <name>x_anbib_grc_action_plan_control_implementation</name>
            <sequence>1</sequence>
            <sys_created_by>marcos.michalski@alparservice.com.br</sys_created_by>
            <sys_created_on>2020-08-11 15:40:03</sys_created_on>
            <sys_domain>global</sys_domain>
            <sys_domain_path>/</sys_domain_path>
            <sys_id>a1439775db22d810faa711494b961903</sys_id>
            <sys_mod_count>2</sys_mod_count>
            <sys_updated_by>nathalia.zago@alparservice.com.br</sys_updated_by>
            <sys_updated_on>2020-09-08 13:50:25</sys_updated_on>
            <value>2</value>
        </sys_choice>
        <sys_choice action="INSERT_OR_UPDATE">
            <dependent_value/>
            <element>state</element>
            <hint/>
            <inactive>false</inactive>
            <label>Reproved</label>
            <language>en</language>
            <name>x_anbib_grc_action_plan_control_implementation</name>
            <sequence>2</sequence>
            <sys_created_by>marcos.michalski@alparservice.com.br</sys_created_by>
            <sys_created_on>2020-08-13 13:09:01</sys_created_on>
            <sys_domain>global</sys_domain>
            <sys_domain_path>/</sys_domain_path>
            <sys_id>da0405e6dbe2dc1002085bd05b9619bd</sys_id>
            <sys_mod_count>2</sys_mod_count>
            <sys_updated_by>nathalia.zago@alparservice.com.br</sys_updated_by>
            <sys_updated_on>2020-09-08 13:50:25</sys_updated_on>
            <value>3</value>
        </sys_choice>
        <sys_choice action="INSERT_OR_UPDATE">
            <dependent_value/>
            <element>state</element>
            <hint/>
            <inactive>false</inactive>
            <label>Cancel</label>
            <language>en</language>
            <name>x_anbib_grc_action_plan_control_implementation</name>
            <sequence>3</sequence>
            <sys_created_by>nathalia.zago@alparservice.com.br</sys_created_by>
            <sys_created_on>2020-08-24 13:56:43</sys_created_on>
            <sys_domain>global</sys_domain>
            <sys_domain_path>/</sys_domain_path>
            <sys_id>798879c2db36d4d0faa711494b96193c</sys_id>
            <sys_mod_count>1</sys_mod_count>
            <sys_updated_by>nathalia.zago@alparservice.com.br</sys_updated_by>
            <sys_updated_on>2020-09-08 18:40:37</sys_updated_on>
            <value>13</value>
        </sys_choice>
        <sys_choice action="INSERT_OR_UPDATE">
            <dependent_value/>
            <element>state</element>
            <hint/>
            <inactive>false</inactive>
            <label>Approved - Wait for Implementation</label>
            <language>en</language>
            <name>x_anbib_grc_action_plan_control_implementation</name>
            <sequence>4</sequence>
            <sys_created_by>nathalia.zago@alparservice.com.br</sys_created_by>
            <sys_created_on>2020-09-08 13:50:25</sys_created_on>
            <sys_domain>global</sys_domain>
            <sys_domain_path>/</sys_domain_path>
            <sys_id>77e68b76db875410faa711494b961963</sys_id>
            <sys_mod_count>3</sys_mod_count>
            <sys_updated_by>nathalia.zago@alparservice.com.br</sys_updated_by>
            <sys_updated_on>2020-09-08 18:40:37</sys_updated_on>
            <value>15</value>
        </sys_choice>
        <sys_choice action="INSERT_OR_UPDATE">
            <dependent_value/>
            <element>state</element>
            <hint/>
            <inactive>false</inactive>
            <label>Implementation validation</label>
            <language>en</language>
            <name>x_anbib_grc_action_plan_control_implementation</name>
            <sequence>5</sequence>
            <sys_created_by>nathalia.zago@alparservice.com.br</sys_created_by>
            <sys_created_on>2020-09-08 13:50:25</sys_created_on>
            <sys_domain>global</sys_domain>
            <sys_domain_path>/</sys_domain_path>
            <sys_id>b7e68b76db875410faa711494b961965</sys_id>
            <sys_mod_count>3</sys_mod_count>
            <sys_updated_by>nathalia.zago@alparservice.com.br</sys_updated_by>
            <sys_updated_on>2020-09-08 18:40:37</sys_updated_on>
            <value>16</value>
        </sys_choice>
        <sys_choice action="INSERT_OR_UPDATE">
            <dependent_value/>
            <element>state</element>
            <hint/>
            <inactive>false</inactive>
            <label>Not implemented</label>
            <language>en</language>
            <name>x_anbib_grc_action_plan_control_implementation</name>
            <sequence>6</sequence>
            <sys_created_by>nathalia.zago@alparservice.com.br</sys_created_by>
            <sys_created_on>2020-09-08 13:50:25</sys_created_on>
            <sys_domain>global</sys_domain>
            <sys_domain_path>/</sys_domain_path>
            <sys_id>f7e68b76db875410faa711494b961967</sys_id>
            <sys_mod_count>3</sys_mod_count>
            <sys_updated_by>nathalia.zago@alparservice.com.br</sys_updated_by>
            <sys_updated_on>2020-09-08 18:40:37</sys_updated_on>
            <value>17</value>
        </sys_choice>
        <sys_choice action="INSERT_OR_UPDATE">
            <dependent_value/>
            <element>state</element>
            <hint/>
            <inactive>false</inactive>
            <label>Implemented</label>
            <language>en</language>
            <name>x_anbib_grc_action_plan_control_implementation</name>
            <sequence>7</sequence>
            <sys_created_by>nathalia.zago@alparservice.com.br</sys_created_by>
            <sys_created_on>2020-09-08 18:05:39</sys_created_on>
            <sys_domain>global</sys_domain>
            <sys_domain_path>/</sys_domain_path>
            <sys_id>6a510807db8f5410faa711494b96191b</sys_id>
            <sys_mod_count>1</sys_mod_count>
            <sys_updated_by>nathalia.zago@alparservice.com.br</sys_updated_by>
            <sys_updated_on>2020-09-08 18:40:37</sys_updated_on>
            <value>18</value>
        </sys_choice>
        <sys_choice action="INSERT_OR_UPDATE">
            <dependent_value/>
            <element>state</element>
            <hint/>
            <inactive>false</inactive>
            <label>ETA change</label>
            <language>en</language>
            <name>x_anbib_grc_action_plan_control_implementation</name>
            <sequence>8</sequence>
            <sys_created_by>nathalia.zago@alparservice.com.br</sys_created_by>
            <sys_created_on>2020-09-08 18:40:37</sys_created_on>
            <sys_domain>global</sys_domain>
            <sys_domain_path>/</sys_domain_path>
            <sys_id>fa59844bdb039410faa711494b9619f3</sys_id>
            <sys_mod_count>1</sys_mod_count>
            <sys_updated_by>nathalia.zago@alparservice.com.br</sys_updated_by>
            <sys_updated_on>2020-09-08 18:46:16</sys_updated_on>
            <value>19</value>
        </sys_choice>
        <sys_choice action="INSERT_OR_UPDATE">
            <dependent_value/>
            <element>state</element>
            <hint/>
            <inactive>false</inactive>
            <label>ETA revalidation</label>
            <language>en</language>
            <name>x_anbib_grc_action_plan_control_implementation</name>
            <sequence>9</sequence>
            <sys_created_by>nathalia.zago@alparservice.com.br</sys_created_by>
            <sys_created_on>2020-09-08 18:40:37</sys_created_on>
            <sys_domain>global</sys_domain>
            <sys_domain_path>/</sys_domain_path>
            <sys_id>3e59844bdb039410faa711494b9619f5</sys_id>
            <sys_mod_count>1</sys_mod_count>
            <sys_updated_by>nathalia.zago@alparservice.com.br</sys_updated_by>
            <sys_updated_on>2020-09-08 18:46:17</sys_updated_on>
            <value>20</value>
        </sys_choice>
        <sys_choice action="INSERT_OR_UPDATE">
            <dependent_value/>
            <element>state</element>
            <hint/>
            <inactive>false</inactive>
            <label>ETA approved - Wait for Implementation</label>
            <language>en</language>
            <name>x_anbib_grc_action_plan_control_implementation</name>
            <sequence>10</sequence>
            <sys_created_by>nathalia.zago@alparservice.com.br</sys_created_by>
            <sys_created_on>2020-09-08 18:46:17</sys_created_on>
            <sys_domain>global</sys_domain>
            <sys_domain_path>/</sys_domain_path>
            <sys_id>a5aac0cfdb039410faa711494b9619c5</sys_id>
            <sys_mod_count>0</sys_mod_count>
            <sys_updated_by>nathalia.zago@alparservice.com.br</sys_updated_by>
            <sys_updated_on>2020-09-08 18:46:17</sys_updated_on>
            <value>21</value>
        </sys_choice>
        <sys_choice action="INSERT_OR_UPDATE">
            <dependent_value/>
            <element>state</element>
            <hint/>
            <inactive>false</inactive>
            <label>ETA reproved</label>
            <language>en</language>
            <name>x_anbib_grc_action_plan_control_implementation</name>
            <sequence>11</sequence>
            <sys_created_by>nathalia.zago@alparservice.com.br</sys_created_by>
            <sys_created_on>2020-09-08 18:49:13</sys_created_on>
            <sys_domain>global</sys_domain>
            <sys_domain_path>/</sys_domain_path>
            <sys_id>3c5bc483db439410faa711494b96194d</sys_id>
            <sys_mod_count>0</sys_mod_count>
            <sys_updated_by>nathalia.zago@alparservice.com.br</sys_updated_by>
            <sys_updated_on>2020-09-08 18:49:13</sys_updated_on>
            <value>22</value>
        </sys_choice>
        <sys_choice_set action="INSERT_OR_UPDATE">
            <element>state</element>
            <name>x_anbib_grc_action_plan_control_implementation</name>
            <sys_class_name>sys_choice_set</sys_class_name>
            <sys_created_by>marcos.michalski@alparservice.com.br</sys_created_by>
            <sys_created_on>2020-08-11 15:26:03</sys_created_on>
            <sys_id>f6e9dfdcdbaf10105ec19785ca96196b</sys_id>
            <sys_mod_count>0</sys_mod_count>
            <sys_name>state</sys_name>
            <sys_package display_value="GRC" source="x_anbib_grc">1a6d93de1b6d58504aae202a2d4bcbdc</sys_package>
            <sys_policy/>
            <sys_scope display_value="GRC">1a6d93de1b6d58504aae202a2d4bcbdc</sys_scope>
            <sys_update_name>sys_choice_x_anbib_grc_action_plan_control_implementation_state</sys_update_name>
            <sys_updated_by>marcos.michalski@alparservice.com.br</sys_updated_by>
            <sys_updated_on>2020-08-11 15:26:03</sys_updated_on>
        </sys_choice_set>
    </sys_choice>
</record_update>
