<?xml version="1.0" encoding="UTF-8"?><record_update table="wf_workflow_version">
    <wf_workflow_version action="INSERT_OR_UPDATE">
        <active>true</active>
        <activity_stages>{"subflows":[],"activities":{},"stages":{},"ends":["1cf019a6db625410faa711494b961932"]}</activity_stages>
        <after_business_rules>false</after_business_rules>
        <checked_out/>
        <checked_out_by/>
        <column_renderer display_value="Workflow-driven">a56213111b030100adca1e094f0713ac</column_renderer>
        <condition/>
        <condition_type/>
        <description/>
        <expected_sequences>1cf095a6db625410faa711494b9619a2,9cf095a6db625410faa711494b9619a0,d8f095a6db625410faa711494b9619a3,1cf019a6db625410faa711494b961932</expected_sequences>
        <expected_time>1970-01-01 14:00:00</expected_time>
        <expected_time_type/>
        <full_sequences>1cf095a6db625410faa711494b9619a2,9cf095a6db625410faa711494b9619a0,d8f095a6db625410faa711494b9619a3,1cf019a6db625410faa711494b961932</full_sequences>
        <journal/>
        <max_activity_count>100</max_activity_count>
        <name>GRC - Control Implementation</name>
        <not_cacheable>false</not_cacheable>
        <on_cancel><![CDATA[// This script executes if the workflow is cancelled.// The global variable context_sys_id contains the sys_id of the cancelled workflow context.]]></on_cancel>
        <order>100</order>
        <pin_type>set_by_activity</pin_type>
        <published>true</published>
        <relative_duration/>
        <requires_ert>true</requires_ert>
        <run_multiple>false</run_multiple>
        <schedule/>
        <stage_field/>
        <stage_order>computed</stage_order>
        <start display_value="Begin">1cf095a6db625410faa711494b9619a2</start>
        <sys_created_by>nathalia.zago@alparservice.com.br</sys_created_by>
        <sys_created_on>2020-08-13 14:05:02</sys_created_on>
        <sys_id>9cf095a6db625410faa711494b96199e</sys_id>
        <sys_mod_count>6</sys_mod_count>
        <sys_updated_by>nathalia.zago@alparservice.com.br</sys_updated_by>
        <sys_updated_on>2020-08-13 14:08:39</sys_updated_on>
        <table>x_anbib_grc_control</table>
        <timezone/>
        <validated>true</validated>
        <workflow display_value="GRC - Control Implementation">d40ba386db661c1002085bd05b9619a8</workflow>
    </wf_workflow_version>
    <wf_workflow action="INSERT_OR_UPDATE">
        <access>public</access>
        <description/>
        <name>GRC - Control Implementation</name>
        <preview/>
        <sys_class_name>wf_workflow</sys_class_name>
        <sys_created_by>nathalia.zago@alparservice.com.br</sys_created_by>
        <sys_created_on>2020-08-12 12:01:10</sys_created_on>
        <sys_domain>global</sys_domain>
        <sys_domain_path>/</sys_domain_path>
        <sys_id>d40ba386db661c1002085bd05b9619a8</sys_id>
        <sys_mod_count>0</sys_mod_count>
        <sys_name>GRC - Control Implementation</sys_name>
        <sys_overrides/>
        <sys_package display_value="GRC" source="x_anbib_grc">1a6d93de1b6d58504aae202a2d4bcbdc</sys_package>
        <sys_policy/>
        <sys_scope display_value="GRC">1a6d93de1b6d58504aae202a2d4bcbdc</sys_scope>
        <sys_update_name>wf_workflow_d40ba386db661c1002085bd05b9619a8</sys_update_name>
        <sys_updated_by>nathalia.zago@alparservice.com.br</sys_updated_by>
        <sys_updated_on>2020-08-12 12:01:10</sys_updated_on>
        <table>x_anbib_grc_control</table>
        <template>false</template>
        <vars/>
    </wf_workflow>
    <wf_activity action="INSERT_OR_UPDATE">
        <activity_definition display_value="Begin">c7a5e32c0a0a0b3a002377c24ed8ea76</activity_definition>
        <activity_definition_updated>false</activity_definition_updated>
        <databus_lookup_id>1</databus_lookup_id>
        <height/>
        <input/>
        <is_parent>false</is_parent>
        <name>Begin</name>
        <new_activity_definition/>
        <notes/>
        <out_of_date>false</out_of_date>
        <parent/>
        <pinned>false</pinned>
        <pinned_version/>
        <stage/>
        <sys_created_by>nathalia.zago@alparservice.com.br</sys_created_by>
        <sys_created_on>2020-08-13 14:05:02</sys_created_on>
        <sys_id>1cf095a6db625410faa711494b9619a2</sys_id>
        <sys_mod_count>0</sys_mod_count>
        <sys_updated_by>nathalia.zago@alparservice.com.br</sys_updated_by>
        <sys_updated_on>2020-08-13 14:05:02</sys_updated_on>
        <timeout>1970-01-01 00:00:00</timeout>
        <vars/>
        <width>80</width>
        <workflow_version display_value="GRC - Control Implementation">9cf095a6db625410faa711494b96199e</workflow_version>
        <x>20</x>
        <y>20</y>
    </wf_activity>
    <sys_variable_value action="delete_multiple" query="document_key=1cf095a6db625410faa711494b9619a2"/>
    <wf_condition action="INSERT_OR_UPDATE">
        <activity display_value="Begin">1cf095a6db625410faa711494b9619a2</activity>
        <condition>true</condition>
        <condition_default/>
        <condition_type>standard</condition_type>
        <else_flag>false</else_flag>
        <error>false</error>
        <event>false</event>
        <event_name/>
        <is_positive>true</is_positive>
        <name>Always</name>
        <order>0</order>
        <short_description/>
        <skip_during_generate>false</skip_during_generate>
        <sys_created_by>nathalia.zago@alparservice.com.br</sys_created_by>
        <sys_created_on>2020-08-13 14:05:02</sys_created_on>
        <sys_id>14f095a6db625410faa711494b9619a3</sys_id>
        <sys_mod_count>0</sys_mod_count>
        <sys_updated_by>nathalia.zago@alparservice.com.br</sys_updated_by>
        <sys_updated_on>2020-08-13 14:05:02</sys_updated_on>
    </wf_condition>
    <wf_activity action="INSERT_OR_UPDATE">
        <activity_definition display_value="End">c7a66f7d0a0a0b3a004544a6d2f14076</activity_definition>
        <activity_definition_updated>false</activity_definition_updated>
        <databus_lookup_id>2</databus_lookup_id>
        <height/>
        <input/>
        <is_parent>false</is_parent>
        <name>End</name>
        <new_activity_definition/>
        <notes/>
        <out_of_date>false</out_of_date>
        <parent/>
        <pinned>false</pinned>
        <pinned_version/>
        <stage/>
        <sys_created_by>nathalia.zago@alparservice.com.br</sys_created_by>
        <sys_created_on>2020-08-13 14:05:02</sys_created_on>
        <sys_id>1cf019a6db625410faa711494b961932</sys_id>
        <sys_mod_count>0</sys_mod_count>
        <sys_updated_by>nathalia.zago@alparservice.com.br</sys_updated_by>
        <sys_updated_on>2020-08-13 14:05:02</sys_updated_on>
        <timeout>1970-01-01 00:00:00</timeout>
        <vars/>
        <width>80</width>
        <workflow_version display_value="GRC - Control Implementation">9cf095a6db625410faa711494b96199e</workflow_version>
        <x>1417</x>
        <y>697</y>
    </wf_activity>
    <sys_variable_value action="delete_multiple" query="document_key=1cf019a6db625410faa711494b961932"/>
    <wf_activity action="INSERT_OR_UPDATE">
        <activity_definition display_value="Run Script">db8c65aec0a8016501d00259bc7203a4</activity_definition>
        <activity_definition_updated>false</activity_definition_updated>
        <databus_lookup_id>4</databus_lookup_id>
        <height/>
        <input>{}</input>
        <is_parent>false</is_parent>
        <name>Trigger parent workflow</name>
        <new_activity_definition/>
        <notes/>
        <out_of_date>false</out_of_date>
        <parent/>
        <pinned>false</pinned>
        <pinned_version/>
        <stage/>
        <sys_created_by>nathalia.zago@alparservice.com.br</sys_created_by>
        <sys_created_on>2020-08-13 14:05:02</sys_created_on>
        <sys_id>d8f095a6db625410faa711494b9619a3</sys_id>
        <sys_mod_count>1</sys_mod_count>
        <sys_updated_by>nathalia.zago@alparservice.com.br</sys_updated_by>
        <sys_updated_on>2020-08-13 14:05:57</sys_updated_on>
        <timeout>1970-01-01 00:00:00</timeout>
        <vars/>
        <width/>
        <workflow_version display_value="GRC - Control Implementation">9cf095a6db625410faa711494b96199e</workflow_version>
        <x>1245</x>
        <y>594</y>
    </wf_activity>
    <sys_variable_value action="delete_multiple" query="document_key=d8f095a6db625410faa711494b9619a3"/>
    <sys_variable_value action="INSERT_OR_UPDATE">
        <document>wf_activity</document>
        <document_key>d8f095a6db625410faa711494b9619a3</document_key>
        <order>1</order>
        <sys_class_name>sys_variable_value</sys_class_name>
        <sys_created_by>nathalia.zago@alparservice.com.br</sys_created_by>
        <sys_created_on>2020-08-13 14:05:02</sys_created_on>
        <sys_id>dcf095a6db625410faa711494b9619a3</sys_id>
        <sys_mod_count>1</sys_mod_count>
        <sys_updated_by>nathalia.zago@alparservice.com.br</sys_updated_by>
        <sys_updated_on>2020-08-13 14:05:57</sys_updated_on>
        <value>gs.info('[ALP1308] ' + workflow.variables.u_fatherwkf);&#13;
var wf = new global.Workflow();&#13;
wf.broadcastEvent(workflow.variables.u_fatherwkf, "CONTROL_VALIDATION");</value>
        <variable display_value="">c35ddef20a0a0ba96248a7090eccd518</variable>
    </sys_variable_value>
    <sys_variable_value action="INSERT_OR_UPDATE">
        <document>wf_activity</document>
        <document_key>d8f095a6db625410faa711494b9619a3</document_key>
        <order>1</order>
        <sys_class_name>sys_variable_value</sys_class_name>
        <sys_created_by>nathalia.zago@alparservice.com.br</sys_created_by>
        <sys_created_on>2020-08-13 14:05:02</sys_created_on>
        <sys_id>dcf095a6db625410faa711494b9619a3</sys_id>
        <sys_mod_count>1</sys_mod_count>
        <sys_updated_by>nathalia.zago@alparservice.com.br</sys_updated_by>
        <sys_updated_on>2020-08-13 14:05:57</sys_updated_on>
        <value>gs.info('[ALP1308] ' + workflow.variables.u_fatherwkf);&#13;
var wf = new global.Workflow();&#13;
wf.broadcastEvent(workflow.variables.u_fatherwkf, "CONTROL_VALIDATION");</value>
        <variable display_value="">c35ddef20a0a0ba96248a7090eccd518</variable>
    </sys_variable_value>
    <wf_condition action="INSERT_OR_UPDATE">
        <activity display_value="Trigger parent workflow">d8f095a6db625410faa711494b9619a3</activity>
        <condition>true</condition>
        <condition_default/>
        <condition_type>standard</condition_type>
        <else_flag>false</else_flag>
        <error>false</error>
        <event>false</event>
        <event_name/>
        <is_positive>true</is_positive>
        <name>Always</name>
        <order>0</order>
        <short_description/>
        <skip_during_generate>false</skip_during_generate>
        <sys_created_by>nathalia.zago@alparservice.com.br</sys_created_by>
        <sys_created_on>2020-08-13 14:05:02</sys_created_on>
        <sys_id>94f095a6db625410faa711494b9619a4</sys_id>
        <sys_mod_count>0</sys_mod_count>
        <sys_updated_by>nathalia.zago@alparservice.com.br</sys_updated_by>
        <sys_updated_on>2020-08-13 14:05:02</sys_updated_on>
    </wf_condition>
    <wf_activity action="INSERT_OR_UPDATE">
        <activity_definition display_value="Wait for condition">d93a02ae0a0a0aa30077abad3fdac035</activity_definition>
        <activity_definition_updated>false</activity_definition_updated>
        <databus_lookup_id>3</databus_lookup_id>
        <height/>
        <input>{}</input>
        <is_parent>false</is_parent>
        <name>Wait for owner definition</name>
        <new_activity_definition/>
        <notes/>
        <out_of_date>false</out_of_date>
        <parent/>
        <pinned>false</pinned>
        <pinned_version/>
        <stage/>
        <sys_created_by>nathalia.zago@alparservice.com.br</sys_created_by>
        <sys_created_on>2020-08-13 14:05:02</sys_created_on>
        <sys_id>9cf095a6db625410faa711494b9619a0</sys_id>
        <sys_mod_count>0</sys_mod_count>
        <sys_updated_by>nathalia.zago@alparservice.com.br</sys_updated_by>
        <sys_updated_on>2020-08-13 14:05:02</sys_updated_on>
        <timeout>1970-01-01 00:00:00</timeout>
        <vars/>
        <width/>
        <workflow_version display_value="GRC - Control Implementation">9cf095a6db625410faa711494b96199e</workflow_version>
        <x>281</x>
        <y>150</y>
    </wf_activity>
    <sys_variable_value action="delete_multiple" query="document_key=9cf095a6db625410faa711494b9619a0"/>
    <sys_variable_value action="INSERT_OR_UPDATE">
        <document>wf_activity</document>
        <document_key>9cf095a6db625410faa711494b9619a0</document_key>
        <order>2</order>
        <sys_class_name>sys_variable_value</sys_class_name>
        <sys_created_by>nathalia.zago@alparservice.com.br</sys_created_by>
        <sys_created_on>2020-08-13 14:05:02</sys_created_on>
        <sys_id>14f095a6db625410faa711494b9619a1</sys_id>
        <sys_mod_count>0</sys_mod_count>
        <sys_updated_by>nathalia.zago@alparservice.com.br</sys_updated_by>
        <sys_updated_on>2020-08-13 14:05:02</sys_updated_on>
        <value>// Set the variable 'answer' to true or false to indicate if the condition has been met or not.&#13;
answer = true;&#13;
</value>
        <variable display_value="">c35debce0a0a0ba96248a709440cf31a</variable>
    </sys_variable_value>
    <sys_variable_value action="INSERT_OR_UPDATE">
        <document>wf_activity</document>
        <document_key>9cf095a6db625410faa711494b9619a0</document_key>
        <order>1</order>
        <sys_class_name>sys_variable_value</sys_class_name>
        <sys_created_by>nathalia.zago@alparservice.com.br</sys_created_by>
        <sys_created_on>2020-08-13 14:05:02</sys_created_on>
        <sys_id>1cf095a6db625410faa711494b9619a1</sys_id>
        <sys_mod_count>0</sys_mod_count>
        <sys_updated_by>nathalia.zago@alparservice.com.br</sys_updated_by>
        <sys_updated_on>2020-08-13 14:05:02</sys_updated_on>
        <value>ownerISNOTEMPTY^EQ</value>
        <variable display_value="">c35dc4cd0a0a0ba96248a70990c1ac54</variable>
    </sys_variable_value>
    <sys_variable_value action="INSERT_OR_UPDATE">
        <document>wf_activity</document>
        <document_key>9cf095a6db625410faa711494b9619a0</document_key>
        <order>1</order>
        <sys_class_name>sys_variable_value</sys_class_name>
        <sys_created_by>nathalia.zago@alparservice.com.br</sys_created_by>
        <sys_created_on>2020-08-13 14:05:02</sys_created_on>
        <sys_id>1cf095a6db625410faa711494b9619a1</sys_id>
        <sys_mod_count>0</sys_mod_count>
        <sys_updated_by>nathalia.zago@alparservice.com.br</sys_updated_by>
        <sys_updated_on>2020-08-13 14:05:02</sys_updated_on>
        <value>ownerISNOTEMPTY^EQ</value>
        <variable display_value="">c35dc4cd0a0a0ba96248a70990c1ac54</variable>
    </sys_variable_value>
    <sys_variable_value action="INSERT_OR_UPDATE">
        <document>wf_activity</document>
        <document_key>9cf095a6db625410faa711494b9619a0</document_key>
        <order>2</order>
        <sys_class_name>sys_variable_value</sys_class_name>
        <sys_created_by>nathalia.zago@alparservice.com.br</sys_created_by>
        <sys_created_on>2020-08-13 14:05:02</sys_created_on>
        <sys_id>14f095a6db625410faa711494b9619a1</sys_id>
        <sys_mod_count>0</sys_mod_count>
        <sys_updated_by>nathalia.zago@alparservice.com.br</sys_updated_by>
        <sys_updated_on>2020-08-13 14:05:02</sys_updated_on>
        <value>// Set the variable 'answer' to true or false to indicate if the condition has been met or not.&#13;
answer = true;&#13;
</value>
        <variable display_value="">c35debce0a0a0ba96248a709440cf31a</variable>
    </sys_variable_value>
    <wf_condition action="INSERT_OR_UPDATE">
        <activity display_value="Wait for owner definition">9cf095a6db625410faa711494b9619a0</activity>
        <condition>true</condition>
        <condition_default/>
        <condition_type>standard</condition_type>
        <else_flag>false</else_flag>
        <error>false</error>
        <event>false</event>
        <event_name/>
        <is_positive>true</is_positive>
        <name>Always</name>
        <order>0</order>
        <short_description/>
        <skip_during_generate>false</skip_during_generate>
        <sys_created_by>nathalia.zago@alparservice.com.br</sys_created_by>
        <sys_created_on>2020-08-13 14:05:02</sys_created_on>
        <sys_id>d0f095a6db625410faa711494b9619a2</sys_id>
        <sys_mod_count>0</sys_mod_count>
        <sys_updated_by>nathalia.zago@alparservice.com.br</sys_updated_by>
        <sys_updated_on>2020-08-13 14:05:02</sys_updated_on>
    </wf_condition>
    <wf_transition action="INSERT_OR_UPDATE">
        <condition display_value="Always">14f095a6db625410faa711494b9619a3</condition>
        <from display_value="Begin">1cf095a6db625410faa711494b9619a2</from>
        <sys_created_by>nathalia.zago@alparservice.com.br</sys_created_by>
        <sys_created_on>2020-08-13 14:05:02</sys_created_on>
        <sys_id>d4f019a6db625410faa711494b961934</sys_id>
        <sys_mod_count>0</sys_mod_count>
        <sys_updated_by>nathalia.zago@alparservice.com.br</sys_updated_by>
        <sys_updated_on>2020-08-13 14:05:02</sys_updated_on>
        <to display_value="Wait for owner definition">9cf095a6db625410faa711494b9619a0</to>
    </wf_transition>
    <wf_transition action="INSERT_OR_UPDATE">
        <condition display_value="Always">94f095a6db625410faa711494b9619a4</condition>
        <from display_value="Trigger parent workflow">d8f095a6db625410faa711494b9619a3</from>
        <sys_created_by>nathalia.zago@alparservice.com.br</sys_created_by>
        <sys_created_on>2020-08-13 14:05:02</sys_created_on>
        <sys_id>d8f019a6db625410faa711494b961934</sys_id>
        <sys_mod_count>0</sys_mod_count>
        <sys_updated_by>nathalia.zago@alparservice.com.br</sys_updated_by>
        <sys_updated_on>2020-08-13 14:05:02</sys_updated_on>
        <to display_value="End">1cf019a6db625410faa711494b961932</to>
    </wf_transition>
    <wf_transition action="INSERT_OR_UPDATE">
        <condition display_value="Always">d0f095a6db625410faa711494b9619a2</condition>
        <from display_value="Wait for owner definition">9cf095a6db625410faa711494b9619a0</from>
        <sys_created_by>nathalia.zago@alparservice.com.br</sys_created_by>
        <sys_created_on>2020-08-13 14:05:02</sys_created_on>
        <sys_id>dcf019a6db625410faa711494b961934</sys_id>
        <sys_mod_count>0</sys_mod_count>
        <sys_updated_by>nathalia.zago@alparservice.com.br</sys_updated_by>
        <sys_updated_on>2020-08-13 14:05:02</sys_updated_on>
        <to display_value="Trigger parent workflow">d8f095a6db625410faa711494b9619a3</to>
    </wf_transition>
    <var_dictionary action="INSERT_OR_UPDATE">
        <active>true</active>
        <array>false</array>
        <array_denormalized>false</array_denormalized>
        <attributes/>
        <audit>false</audit>
        <calculation><![CDATA[(function calculatedFieldValue(current) {

	// Add your code here
	return '';  // return the calculated value

})(current);]]></calculation>
        <choice/>
        <choice_field/>
        <choice_table/>
        <column_label>record</column_label>
        <comments/>
        <create_roles/>
        <default_value/>
        <defaultsort/>
        <delete_roles/>
        <dependent/>
        <dependent_on_field/>
        <display>false</display>
        <dynamic_creation>false</dynamic_creation>
        <dynamic_creation_script/>
        <dynamic_default_value/>
        <dynamic_ref_qual/>
        <element>u_record</element>
        <element_reference>false</element_reference>
        <foreign_database/>
        <function_definition/>
        <function_field>false</function_field>
        <help/>
        <hint/>
        <internal_type display_value="String">string</internal_type>
        <label>record</label>
        <mandatory>false</mandatory>
        <max_length>32</max_length>
        <model_id>d40ba386db661c1002085bd05b9619a8</model_id>
        <model_table>wf_workflow</model_table>
        <name>var__m_var_dictionary_d40ba386db661c1002085bd05b9619a8</name>
        <next_element/>
        <order>100</order>
        <primary>false</primary>
        <read_only>false</read_only>
        <read_roles/>
        <reference/>
        <reference_cascade_rule/>
        <reference_floats>false</reference_floats>
        <reference_key/>
        <reference_qual/>
        <reference_qual_condition/>
        <reference_type/>
        <sizeclass/>
        <spell_check>false</spell_check>
        <staged>false</staged>
        <sys_class_name>var_dictionary</sys_class_name>
        <sys_created_by>nathalia.zago@alparservice.com.br</sys_created_by>
        <sys_created_on>2020-08-13 13:52:49</sys_created_on>
        <sys_id>061ec1eedb225410faa711494b961917</sys_id>
        <sys_mod_count>1</sys_mod_count>
        <sys_name>record</sys_name>
        <sys_package display_value="GRC" source="x_anbib_grc">1a6d93de1b6d58504aae202a2d4bcbdc</sys_package>
        <sys_policy/>
        <sys_scope display_value="GRC">1a6d93de1b6d58504aae202a2d4bcbdc</sys_scope>
        <sys_update_name>var_dictionary_061ec1eedb225410faa711494b961917</sys_update_name>
        <sys_updated_by>nathalia.zago@alparservice.com.br</sys_updated_by>
        <sys_updated_on>2020-08-13 13:52:49</sys_updated_on>
        <table_reference>false</table_reference>
        <text_index>false</text_index>
        <unique>false</unique>
        <use_dependent_field>false</use_dependent_field>
        <use_dynamic_default>false</use_dynamic_default>
        <use_reference_qualifier>simple</use_reference_qualifier>
        <virtual>false</virtual>
        <widget/>
        <write_roles/>
        <xml_view>false</xml_view>
    </var_dictionary>
    <var_dictionary action="INSERT_OR_UPDATE">
        <active>true</active>
        <array>false</array>
        <array_denormalized>false</array_denormalized>
        <attributes/>
        <audit>false</audit>
        <calculation><![CDATA[(function calculatedFieldValue(current) {

	// Add your code here
	return '';  // return the calculated value

})(current);]]></calculation>
        <choice/>
        <choice_field/>
        <choice_table/>
        <column_label>Control</column_label>
        <comments/>
        <create_roles/>
        <default_value/>
        <defaultsort/>
        <delete_roles/>
        <dependent/>
        <dependent_on_field/>
        <display>false</display>
        <dynamic_creation>false</dynamic_creation>
        <dynamic_creation_script/>
        <dynamic_default_value/>
        <dynamic_ref_qual/>
        <element>u_control</element>
        <element_reference>false</element_reference>
        <foreign_database/>
        <function_definition/>
        <function_field>false</function_field>
        <help/>
        <hint/>
        <internal_type display_value="Reference">reference</internal_type>
        <label>Control</label>
        <mandatory>false</mandatory>
        <max_length>32</max_length>
        <model_id>d40ba386db661c1002085bd05b9619a8</model_id>
        <model_table>wf_workflow</model_table>
        <name>var__m_var_dictionary_d40ba386db661c1002085bd05b9619a8</name>
        <next_element/>
        <order>100</order>
        <primary>false</primary>
        <read_only>false</read_only>
        <read_roles/>
        <reference display_value="" name="x_anbib_grc_control_template">x_anbib_grc_control_template</reference>
        <reference_cascade_rule/>
        <reference_floats>false</reference_floats>
        <reference_key/>
        <reference_qual/>
        <reference_qual_condition/>
        <reference_type/>
        <sizeclass/>
        <spell_check>false</spell_check>
        <staged>false</staged>
        <sys_class_name>var_dictionary</sys_class_name>
        <sys_created_by>nathalia.zago@alparservice.com.br</sys_created_by>
        <sys_created_on>2020-08-12 13:14:16</sys_created_on>
        <sys_id>1d8b770edba61c1002085bd05b961934</sys_id>
        <sys_mod_count>2</sys_mod_count>
        <sys_name>Control</sys_name>
        <sys_package display_value="GRC" source="x_anbib_grc">1a6d93de1b6d58504aae202a2d4bcbdc</sys_package>
        <sys_policy/>
        <sys_scope display_value="GRC">1a6d93de1b6d58504aae202a2d4bcbdc</sys_scope>
        <sys_update_name>var_dictionary_1d8b770edba61c1002085bd05b961934</sys_update_name>
        <sys_updated_by>nathalia.zago@alparservice.com.br</sys_updated_by>
        <sys_updated_on>2020-08-12 13:16:03</sys_updated_on>
        <table_reference>false</table_reference>
        <text_index>false</text_index>
        <unique>false</unique>
        <use_dependent_field>false</use_dependent_field>
        <use_dynamic_default>false</use_dynamic_default>
        <use_reference_qualifier>simple</use_reference_qualifier>
        <virtual>false</virtual>
        <widget/>
        <write_roles/>
        <xml_view>false</xml_view>
    </var_dictionary>
    <var_dictionary action="INSERT_OR_UPDATE">
        <active>true</active>
        <array>false</array>
        <array_denormalized>false</array_denormalized>
        <attributes/>
        <audit>false</audit>
        <calculation><![CDATA[(function calculatedFieldValue(current) {

	// Add your code here
	return '';  // return the calculated value

})(current);]]></calculation>
        <choice/>
        <choice_field/>
        <choice_table/>
        <column_label>fatherWKF</column_label>
        <comments/>
        <create_roles/>
        <default_value/>
        <defaultsort/>
        <delete_roles/>
        <dependent/>
        <dependent_on_field/>
        <display>false</display>
        <dynamic_creation>false</dynamic_creation>
        <dynamic_creation_script/>
        <dynamic_default_value/>
        <dynamic_ref_qual/>
        <element>u_fatherwkf</element>
        <element_reference>false</element_reference>
        <foreign_database/>
        <function_definition/>
        <function_field>false</function_field>
        <help/>
        <hint/>
        <internal_type display_value="String">string</internal_type>
        <label>fatherWKF</label>
        <mandatory>false</mandatory>
        <max_length>32</max_length>
        <model_id>d40ba386db661c1002085bd05b9619a8</model_id>
        <model_table>wf_workflow</model_table>
        <name>var__m_var_dictionary_d40ba386db661c1002085bd05b9619a8</name>
        <next_element/>
        <order>100</order>
        <primary>false</primary>
        <read_only>false</read_only>
        <read_roles/>
        <reference/>
        <reference_cascade_rule/>
        <reference_floats>false</reference_floats>
        <reference_key/>
        <reference_qual/>
        <reference_qual_condition/>
        <reference_type/>
        <sizeclass/>
        <spell_check>false</spell_check>
        <staged>false</staged>
        <sys_class_name>var_dictionary</sys_class_name>
        <sys_created_by>nathalia.zago@alparservice.com.br</sys_created_by>
        <sys_created_on>2020-08-13 13:52:29</sys_created_on>
        <sys_id>39fd01eedb225410faa711494b961908</sys_id>
        <sys_mod_count>1</sys_mod_count>
        <sys_name>fatherWKF</sys_name>
        <sys_package display_value="GRC" source="x_anbib_grc">1a6d93de1b6d58504aae202a2d4bcbdc</sys_package>
        <sys_policy/>
        <sys_scope display_value="GRC">1a6d93de1b6d58504aae202a2d4bcbdc</sys_scope>
        <sys_update_name>var_dictionary_39fd01eedb225410faa711494b961908</sys_update_name>
        <sys_updated_by>nathalia.zago@alparservice.com.br</sys_updated_by>
        <sys_updated_on>2020-08-13 13:52:30</sys_updated_on>
        <table_reference>false</table_reference>
        <text_index>false</text_index>
        <unique>false</unique>
        <use_dependent_field>false</use_dependent_field>
        <use_dynamic_default>false</use_dynamic_default>
        <use_reference_qualifier>simple</use_reference_qualifier>
        <virtual>false</virtual>
        <widget/>
        <write_roles/>
        <xml_view>false</xml_view>
    </var_dictionary>
    <var_dictionary action="INSERT_OR_UPDATE">
        <active>true</active>
        <array>false</array>
        <array_denormalized>false</array_denormalized>
        <attributes/>
        <audit>false</audit>
        <calculation><![CDATA[(function calculatedFieldValue(current) {

	// Add your code here
	return '';  // return the calculated value

})(current);]]></calculation>
        <choice/>
        <choice_field/>
        <choice_table/>
        <column_label>Entity</column_label>
        <comments/>
        <create_roles/>
        <default_value/>
        <defaultsort/>
        <delete_roles/>
        <dependent/>
        <dependent_on_field/>
        <display>false</display>
        <dynamic_creation>false</dynamic_creation>
        <dynamic_creation_script/>
        <dynamic_default_value/>
        <dynamic_ref_qual/>
        <element>u_entity</element>
        <element_reference>false</element_reference>
        <foreign_database/>
        <function_definition/>
        <function_field>false</function_field>
        <help/>
        <hint/>
        <internal_type display_value="Reference">reference</internal_type>
        <label>Entity</label>
        <mandatory>false</mandatory>
        <max_length>32</max_length>
        <model_id>d40ba386db661c1002085bd05b9619a8</model_id>
        <model_table>wf_workflow</model_table>
        <name>var__m_var_dictionary_d40ba386db661c1002085bd05b9619a8</name>
        <next_element/>
        <order>100</order>
        <primary>false</primary>
        <read_only>false</read_only>
        <read_roles/>
        <reference display_value="" name="x_anbib_grc_entity">x_anbib_grc_entity</reference>
        <reference_cascade_rule/>
        <reference_floats>false</reference_floats>
        <reference_key/>
        <reference_qual/>
        <reference_qual_condition/>
        <reference_type/>
        <sizeclass/>
        <spell_check>false</spell_check>
        <staged>false</staged>
        <sys_class_name>var_dictionary</sys_class_name>
        <sys_created_by>nathalia.zago@alparservice.com.br</sys_created_by>
        <sys_created_on>2020-08-12 13:13:14</sys_created_on>
        <sys_id>416bb30edba61c1002085bd05b9619f6</sys_id>
        <sys_mod_count>4</sys_mod_count>
        <sys_name>Entity</sys_name>
        <sys_package display_value="GRC" source="x_anbib_grc">1a6d93de1b6d58504aae202a2d4bcbdc</sys_package>
        <sys_policy/>
        <sys_scope display_value="GRC">1a6d93de1b6d58504aae202a2d4bcbdc</sys_scope>
        <sys_update_name>var_dictionary_416bb30edba61c1002085bd05b9619f6</sys_update_name>
        <sys_updated_by>nathalia.zago@alparservice.com.br</sys_updated_by>
        <sys_updated_on>2020-08-12 13:15:41</sys_updated_on>
        <table_reference>false</table_reference>
        <text_index>false</text_index>
        <unique>false</unique>
        <use_dependent_field>false</use_dependent_field>
        <use_dynamic_default>false</use_dynamic_default>
        <use_reference_qualifier>simple</use_reference_qualifier>
        <virtual>false</virtual>
        <widget/>
        <write_roles/>
        <xml_view>false</xml_view>
    </var_dictionary>
    <var_dictionary action="INSERT_OR_UPDATE">
        <active>true</active>
        <array>false</array>
        <array_denormalized>false</array_denormalized>
        <attributes>allow_invalid=true</attributes>
        <audit>false</audit>
        <calculation><![CDATA[(function calculatedFieldValue(current) {

	// Add your code here
	return '';  // return the calculated value

})(current);]]></calculation>
        <choice/>
        <choice_field/>
        <choice_table/>
        <column_label>Layer</column_label>
        <comments/>
        <create_roles/>
        <default_value/>
        <defaultsort/>
        <delete_roles/>
        <dependent/>
        <dependent_on_field/>
        <display>false</display>
        <dynamic_creation>false</dynamic_creation>
        <dynamic_creation_script/>
        <dynamic_default_value/>
        <dynamic_ref_qual/>
        <element>u_layer</element>
        <element_reference>false</element_reference>
        <foreign_database/>
        <function_definition/>
        <function_field>false</function_field>
        <help/>
        <hint/>
        <internal_type display_value="Reference">reference</internal_type>
        <label>Layer</label>
        <mandatory>false</mandatory>
        <max_length>32</max_length>
        <model_id>d40ba386db661c1002085bd05b9619a8</model_id>
        <model_table>wf_workflow</model_table>
        <name>var__m_var_dictionary_d40ba386db661c1002085bd05b9619a8</name>
        <next_element/>
        <order>100</order>
        <primary>false</primary>
        <read_only>false</read_only>
        <read_roles/>
        <reference display_value="" name="x_anbib_grc_layer_control">x_anbib_grc_layer_control</reference>
        <reference_cascade_rule/>
        <reference_floats>false</reference_floats>
        <reference_key/>
        <reference_qual/>
        <reference_qual_condition/>
        <reference_type/>
        <sizeclass/>
        <spell_check>false</spell_check>
        <staged>false</staged>
        <sys_class_name>var_dictionary</sys_class_name>
        <sys_created_by>nathalia.zago@alparservice.com.br</sys_created_by>
        <sys_created_on>2020-08-12 13:15:22</sys_created_on>
        <sys_id>f8db7f0edba61c1002085bd05b96198e</sys_id>
        <sys_mod_count>1</sys_mod_count>
        <sys_name>var__m_var_dictionary_d40ba386db661c1002085bd05b9619a8</sys_name>
        <sys_package display_value="GRC" source="x_anbib_grc">1a6d93de1b6d58504aae202a2d4bcbdc</sys_package>
        <sys_policy/>
        <sys_scope display_value="GRC">1a6d93de1b6d58504aae202a2d4bcbdc</sys_scope>
        <sys_update_name>var_dictionary_f8db7f0edba61c1002085bd05b96198e</sys_update_name>
        <sys_updated_by>nathalia.zago@alparservice.com.br</sys_updated_by>
        <sys_updated_on>2020-08-12 13:15:23</sys_updated_on>
        <table_reference>false</table_reference>
        <text_index>false</text_index>
        <unique>false</unique>
        <use_dependent_field>false</use_dependent_field>
        <use_dynamic_default>false</use_dynamic_default>
        <use_reference_qualifier>simple</use_reference_qualifier>
        <virtual>false</virtual>
        <widget/>
        <write_roles/>
        <xml_view>false</xml_view>
    </var_dictionary>
    <sys_documentation element="u_layer" language="en" table="var__m_var_dictionary_d40ba386db661c1002085bd05b9619a8">
        <sys_documentation action="INSERT_OR_UPDATE">
            <element>u_layer</element>
            <help/>
            <hint/>
            <label>Layer</label>
            <language>en</language>
            <name>var__m_var_dictionary_d40ba386db661c1002085bd05b9619a8</name>
            <plural>Layer</plural>
            <sys_class_name>sys_documentation</sys_class_name>
            <sys_created_by>nathalia.zago@alparservice.com.br</sys_created_by>
            <sys_created_on>2020-08-12 13:15:22</sys_created_on>
            <sys_id>1bfb734edba61c1002085bd05b96193d</sys_id>
            <sys_mod_count>0</sys_mod_count>
            <sys_name>Layer</sys_name>
            <sys_package display_value="GRC" source="x_anbib_grc">1a6d93de1b6d58504aae202a2d4bcbdc</sys_package>
            <sys_policy/>
            <sys_scope display_value="GRC">1a6d93de1b6d58504aae202a2d4bcbdc</sys_scope>
            <sys_update_name>sys_documentation_var__m_var_dictionary_d40ba386db661c1002085bd05b9619a8_u_layer_en</sys_update_name>
            <sys_updated_by>nathalia.zago@alparservice.com.br</sys_updated_by>
            <sys_updated_on>2020-08-12 13:15:22</sys_updated_on>
            <url/>
            <url_target/>
        </sys_documentation>
    </sys_documentation>
    <sys_documentation element="u_record" language="en" table="var__m_var_dictionary_d40ba386db661c1002085bd05b9619a8">
        <sys_documentation action="INSERT_OR_UPDATE">
            <element>u_record</element>
            <help/>
            <hint/>
            <label>record</label>
            <language>en</language>
            <name>var__m_var_dictionary_d40ba386db661c1002085bd05b9619a8</name>
            <plural>record</plural>
            <sys_class_name>sys_documentation</sys_class_name>
            <sys_created_by>nathalia.zago@alparservice.com.br</sys_created_by>
            <sys_created_on>2020-08-13 13:52:49</sys_created_on>
            <sys_id>1d2ec1eedb225410faa711494b9619e3</sys_id>
            <sys_mod_count>0</sys_mod_count>
            <sys_name>record</sys_name>
            <sys_package display_value="GRC" source="x_anbib_grc">1a6d93de1b6d58504aae202a2d4bcbdc</sys_package>
            <sys_policy/>
            <sys_scope display_value="GRC">1a6d93de1b6d58504aae202a2d4bcbdc</sys_scope>
            <sys_update_name>sys_documentation_var__m_var_dictionary_d40ba386db661c1002085bd05b9619a8_u_record_en</sys_update_name>
            <sys_updated_by>nathalia.zago@alparservice.com.br</sys_updated_by>
            <sys_updated_on>2020-08-13 13:52:49</sys_updated_on>
            <url/>
            <url_target/>
        </sys_documentation>
    </sys_documentation>
    <sys_documentation element="u_fatherwkf" language="en" table="var__m_var_dictionary_d40ba386db661c1002085bd05b9619a8">
        <sys_documentation action="INSERT_OR_UPDATE">
            <element>u_fatherwkf</element>
            <help/>
            <hint/>
            <label>fatherWKF</label>
            <language>en</language>
            <name>var__m_var_dictionary_d40ba386db661c1002085bd05b9619a8</name>
            <plural>fatherWKF</plural>
            <sys_class_name>sys_documentation</sys_class_name>
            <sys_created_by>nathalia.zago@alparservice.com.br</sys_created_by>
            <sys_created_on>2020-08-13 13:52:30</sys_created_on>
            <sys_id>2c1e81eedb225410faa711494b961905</sys_id>
            <sys_mod_count>0</sys_mod_count>
            <sys_name>fatherWKF</sys_name>
            <sys_package display_value="GRC" source="x_anbib_grc">1a6d93de1b6d58504aae202a2d4bcbdc</sys_package>
            <sys_policy/>
            <sys_scope display_value="GRC">1a6d93de1b6d58504aae202a2d4bcbdc</sys_scope>
            <sys_update_name>sys_documentation_var__m_var_dictionary_d40ba386db661c1002085bd05b9619a8_u_fatherwkf_en</sys_update_name>
            <sys_updated_by>nathalia.zago@alparservice.com.br</sys_updated_by>
            <sys_updated_on>2020-08-13 13:52:30</sys_updated_on>
            <url/>
            <url_target/>
        </sys_documentation>
    </sys_documentation>
    <sys_documentation element="u_entity" language="en" table="var__m_var_dictionary_d40ba386db661c1002085bd05b9619a8">
        <sys_documentation action="INSERT_OR_UPDATE">
            <element>u_entity</element>
            <help/>
            <hint/>
            <label>Entity</label>
            <language>en</language>
            <name>var__m_var_dictionary_d40ba386db661c1002085bd05b9619a8</name>
            <plural>Entity</plural>
            <sys_class_name>sys_documentation</sys_class_name>
            <sys_created_by>nathalia.zago@alparservice.com.br</sys_created_by>
            <sys_created_on>2020-08-12 13:13:16</sys_created_on>
            <sys_id>648b370edba61c1002085bd05b9619b9</sys_id>
            <sys_mod_count>1</sys_mod_count>
            <sys_name>Entity</sys_name>
            <sys_package display_value="GRC" source="x_anbib_grc">1a6d93de1b6d58504aae202a2d4bcbdc</sys_package>
            <sys_policy/>
            <sys_scope display_value="GRC">1a6d93de1b6d58504aae202a2d4bcbdc</sys_scope>
            <sys_update_name>sys_documentation_var__m_var_dictionary_d40ba386db661c1002085bd05b9619a8_u_entity_en</sys_update_name>
            <sys_updated_by>nathalia.zago@alparservice.com.br</sys_updated_by>
            <sys_updated_on>2020-08-12 13:14:36</sys_updated_on>
            <url/>
            <url_target/>
        </sys_documentation>
    </sys_documentation>
    <sys_documentation element="u_control" language="en" table="var__m_var_dictionary_d40ba386db661c1002085bd05b9619a8">
        <sys_documentation action="INSERT_OR_UPDATE">
            <element>u_control</element>
            <help/>
            <hint/>
            <label>Control</label>
            <language>en</language>
            <name>var__m_var_dictionary_d40ba386db661c1002085bd05b9619a8</name>
            <plural>Control</plural>
            <sys_class_name>sys_documentation</sys_class_name>
            <sys_created_by>nathalia.zago@alparservice.com.br</sys_created_by>
            <sys_created_on>2020-08-12 13:14:16</sys_created_on>
            <sys_id>c3bbf70edba61c1002085bd05b961919</sys_id>
            <sys_mod_count>0</sys_mod_count>
            <sys_name>Control</sys_name>
            <sys_package display_value="GRC" source="x_anbib_grc">1a6d93de1b6d58504aae202a2d4bcbdc</sys_package>
            <sys_policy/>
            <sys_scope display_value="GRC">1a6d93de1b6d58504aae202a2d4bcbdc</sys_scope>
            <sys_update_name>sys_documentation_var__m_var_dictionary_d40ba386db661c1002085bd05b9619a8_u_control_en</sys_update_name>
            <sys_updated_by>nathalia.zago@alparservice.com.br</sys_updated_by>
            <sys_updated_on>2020-08-12 13:14:16</sys_updated_on>
            <url/>
            <url_target/>
        </sys_documentation>
    </sys_documentation>
    <wf_estimated_runtime_config action="INSERT_OR_UPDATE">
        <estimated_run_time/>
        <no_of_data_points>1</no_of_data_points>
        <percentage_threshold_ert>20</percentage_threshold_ert>
        <sys_created_by>nathalia.zago@alparservice.com.br</sys_created_by>
        <sys_created_on>2020-08-13 14:05:02</sys_created_on>
        <sys_id>50f095a6db625410faa711494b96199f</sys_id>
        <sys_mod_count>0</sys_mod_count>
        <sys_updated_by>nathalia.zago@alparservice.com.br</sys_updated_by>
        <sys_updated_on>2020-08-13 14:05:02</sys_updated_on>
        <workflow_version display_value="GRC - Control Implementation">9cf095a6db625410faa711494b96199e</workflow_version>
    </wf_estimated_runtime_config>
    <wf_workflow_version action="update_multiple" query="workflow=d40ba386db661c1002085bd05b9619a8^sys_id!=9cf095a6db625410faa711494b96199e">
        <published>false</published>
    </wf_workflow_version>
</record_update>
